nl2bench/__init__.py
nl2bench/__main__.py
nl2bench/_nl2bench_antlr4_liblogic/logic.interp
nl2bench/_nl2bench_antlr4_liblogic/logic.tokens
nl2bench/_nl2bench_antlr4_liblogic/logicLexer.interp
nl2bench/_nl2bench_antlr4_liblogic/logicLexer.py
nl2bench/_nl2bench_antlr4_liblogic/logicLexer.tokens
nl2bench/_nl2bench_antlr4_liblogic/logicListener.py
nl2bench/_nl2bench_antlr4_liblogic/logicParser.py
nl2bench/_nl2bench_antlr4_liblogic/logicVisitor.py
nl2bench/cell.py
nl2bench/lib_fn_parser.py
nl2bench/nl2bench.py
nl2bench/nl_parser.py
nl2bench-0.12.0.dist-info/METADATA
nl2bench-0.12.0.dist-info/WHEEL
nl2bench-0.12.0.dist-info/entry_points.txt
nl2bench-0.12.0.dist-info/RECORD
