Metadata-Version: 2.3
Name: nl2bench
Version: 0.12.0
Summary: Converts from combinational netlists to the BENCH format for DFT
License: Apache-2.0
Author: Mohamed Gaber
Author-email: me@donn.website
Requires-Python: >=3.10
Classifier: License :: OSI Approved :: Apache Software License
Classifier: Programming Language :: Python :: 3
Classifier: Programming Language :: Python :: 3.10
Classifier: Programming Language :: Python :: 3.11
Classifier: Programming Language :: Python :: 3.12
Classifier: Programming Language :: Python :: 3.13
Requires-Dist: antlr4-python3-runtime (==4.9.*)
Requires-Dist: click (>=8,<9)
Requires-Dist: immutabledict
Requires-Dist: lln_libparse (==0.56.*)
Requires-Dist: pyosys (==0.56.*)
Project-URL: Bug Tracker, https://github.com/donn/nl2bench/issues
Project-URL: Repository, https://github.com/donn/nl2bench
